LICENSE
MANIFEST.in
README.md
setup.cfg
setup.py
versioneer.py
knitty/__init__.py
knitty/_version.py
knitty/api.py
knitty/ast_filter.py
knitty/consts.py
knitty/knitty.py
knitty/pre_knitty.py
knitty/preprocess_filter.py
knitty/self_contained_raw_html_img.py
knitty.egg-info/PKG-INFO
knitty.egg-info/SOURCES.txt
knitty.egg-info/dependency_links.txt
knitty.egg-info/entry_points.txt
knitty.egg-info/requires.txt
knitty.egg-info/top_level.txt
knitty/pandoc_filter_arg/__init__.py
knitty/pandoc_filter_arg/__main__.py
knitty/pandoc_filter_arg/cli.py
knitty/pandoc_filter_arg/pandoc_filter_arg/pandoc_filter_arg.py
knitty/stitch/__init__.py
knitty/stitch/options.py
knitty/stitch/stitch.py
knitty/tools/__init__.py
knitty/tools/tools.py