Metadata-Version: 2.1
Name: knitty
Version: 0.6.1
Summary: Reproducible report generation tool via Jupyter, Pandoc and Markdown.
Home-page: https://github.com/kiwi0fruit/knitty
Author: Peter Zagubisalo
Author-email: peter.zagubisalo@gmail.com
License: MIT License
Keywords: atom hydrogen jupyter pandoc markdown report
Platform: UNKNOWN
Classifier: Development Status :: 3 - Alpha
Classifier: Intended Audience :: Developers
Classifier: Intended Audience :: Science/Research
Classifier: Topic :: Software Development :: Build Tools
Classifier: Topic :: Scientific/Engineering :: Information Analysis
Classifier: License :: OSI Approved :: MIT License
Classifier: Operating System :: OS Independent
Classifier: Programming Language :: Python :: 3
Classifier: Programming Language :: Python :: 3.6
Requires-Python: >=3.6
Provides-Extra: dev
